sdktestadd/__init__.py
sdktestadd/main.py
sdktestadd/core/__init__.py
sdktestadd/core/get_len.py
sdktestadd-0.7.dist-info/LICENSE
sdktestadd-0.7.dist-info/METADATA
sdktestadd-0.7.dist-info/WHEEL
sdktestadd-0.7.dist-info/top_level.txt
sdktestadd-0.7.dist-info/RECORD
