Metadata-Version: 2.1
Name: sdktestadd
Version: 0.7
Summary: SDK about postgres
Author: YaShiko
Author-email: m15339346028@163.com
License: UNKNOWN
Platform: UNKNOWN
Classifier: Programming Language :: Python :: 3
Classifier: License :: OSI Approved :: MIT License
Classifier: Operating System :: OS Independent
Requires-Python: >=3.6
License-File: LICENSE
Requires-Dist: pandas (==1.4.1)
Requires-Dist: numpy (==1.22.1)
